tidal_parser/__init__.py
tidal_parser/tidal_parser.py
tidal_parser-0.0.2.dist-info/LICENSE
tidal_parser-0.0.2.dist-info/METADATA
tidal_parser-0.0.2.dist-info/WHEEL
tidal_parser-0.0.2.dist-info/top_level.txt
tidal_parser-0.0.2.dist-info/RECORD
