Metadata-Version: 2.1
Name: tidal-parser
Version: 0.0.2
Summary: Python parser for binary log files written with the TiDaL C++ logging library
Home-page: https://github.com/dpkoch/tidal
Author: Daniel Koch
Author-email: daniel.p.koch@gmail.com
License: MIT
Project-URL: Bug Tracker, https://github.com/dpkoch/tidal/issues
Project-URL: Documentation, https://github.com/dpkoch/tidal
Project-URL: Source Code, https://github.com/dpkoch/tidal
Platform: UNKNOWN
Classifier: Programming Language :: Python :: 3
Classifier: License :: OSI Approved :: MIT License
Classifier: Operating System :: OS Independent
Requires-Python: >=3.6
License-File: LICENSE
